FastAuthX/__init__.py
FastAuthX/auth_handler.py
FastAuthX/auth_token.py
FastAuthX/database.py
FastAuthX/hashing.py
FastAuthX/oauth2.py
FastAuthX/schemas.py
FastAuthX-1.1.0.dist-info/METADATA
FastAuthX-1.1.0.dist-info/WHEEL
FastAuthX-1.1.0.dist-info/top_level.txt
FastAuthX-1.1.0.dist-info/RECORD
