Metadata-Version: 2.1
Name: FastAuthX
Version: 1.1.0
Summary: A plug-and-play authentication system for FastAPI.
Home-page: https://github.com/emeraldlinks/FastAuthX
Author: Joseph Christopher
Author-email: joechristophersc@gmail.com
Classifier: Programming Language :: Python :: 3.9
Classifier: Framework :: FastAPI
Classifier: License :: OSI Approved :: MIT License
Requires-Dist: fastapi
Requires-Dist: sqlalchemy
Requires-Dist: sqlmodel
Requires-Dist: passlib[bcrypt]
Requires-Dist: python-jose
Requires-Dist: uvicorn
